osmlocator/__init__.py
osmlocator/evaluator.py
osmlocator/osm_locator.py
osmlocator/settings.py
osmlocator/util.py
osmlocator-0.1.1.dist-info/LICENSE
osmlocator-0.1.1.dist-info/METADATA
osmlocator-0.1.1.dist-info/WHEEL
osmlocator-0.1.1.dist-info/top_level.txt
osmlocator-0.1.1.dist-info/RECORD
