Metadata-Version: 2.1
Name: osmlocator
Version: 0.1.1
Summary: A tool for locating overlapping scatter marks.
Home-page: https://github.com/ccqym/OsmLocator
Author: Yuming Qiu
Author-email: ccqiuym@126.com
License: MPL-2.0
Classifier: Intended Audience :: Developers
Classifier: License :: OSI Approved :: Mozilla Public License 2.0 (MPL 2.0)
Classifier: Programming Language :: Python :: 3
Classifier: Operating System :: OS Independent
Classifier: Topic :: Software Development :: Libraries
Classifier: Topic :: Scientific/Engineering :: Image Recognition
Classifier: Topic :: Scientific/Engineering :: Artificial Intelligence
Requires-Python: >=3.8.0
License-File: LICENSE
Requires-Dist: opencv-python >=3.3
Requires-Dist: numpy
